
<item>
<title>Kung Fu Master - Donnie Yen_pt 1_Eng Dub(1994)</title>
<link>https://www.youtube.com/watch?v=P60OxWahxBQ</link>
<thumbnail>https://images-na.ssl-images-amazon.com/images/I/5186AGDFVQL._SY445_.jpg</thumbnail>
</item>

<item>
<title>The Kung Fu Master-Donnie Yen_Pt 2_Eng Dub(1994)</title>
<link>https://www.youtube.com/watch?v=6OElL0tCTD0</link>
<thumbnail>https://images-na.ssl-images-amazon.com/images/I/5186AGDFVQL._SY445_.jpg</thumbnail>
</item>

<item>
<title>Fist of Fury- Donnie Yen- Pt 1_Eng Dub(1995)</title>
<link>https://www.youtube.com/watch?v=E7etM1JJLbY</link>
<thumbnail>https://image.tmdb.org/t/p/w1280/4yUafncTyYuS2CCNmLnDBNhxZKi.jpg</thumbnail>
</item>

<item>
<title>Fist of Fury- Donnie Yen -Pt 2_Eng Dub(1995)</title>
<link>https://www.youtube.com/watch?v=TPqk0o2WOhY</link>
<thumbnail>https://image.tmdb.org/t/p/w1280/4yUafncTyYuS2CCNmLnDBNhxZKi.jpg</thumbnail>
</item>

<item>
<title>Tai Chi Master_Jackie Wu Jing_English Dub(1997)_Pt 1</title>
<link>https://www.youtube.com/watch?v=py2JmhxJBR0</link>
<thumbnail></thumbnail>
</item>

<item>
<title>Tai Chi Master_Jackie Wu Jing_English Dub(1997)_Pt 2</title>
<link>https://www.youtube.com/watch?v=NFKiX3PWp64&t=136s</link>
<thumbnail></thumbnail>
</item>

<item>
<title>Shaolin Vs Evil Dead 1</title>
<link>https://www.youtube.com/watch?v=ay-uQpOfu24</link>
<thumbnail></thumbnail>
</item>

<item>
<title>Shaolin Vs Evil Dead 2</title>
<link>https://www.youtube.com/watch?v=KqDndRnnyYo</link>
<thumbnail></thumbnail>
</item>
